jax_sgmc/__init__.py
jax_sgmc/adaption.py
jax_sgmc/alias.py
jax_sgmc/integrator.py
jax_sgmc/io.py
jax_sgmc/potential.py
jax_sgmc/scheduler.py
jax_sgmc/solver.py
jax_sgmc/version.py
jax_sgmc/data/__init__.py
jax_sgmc/data/core.py
jax_sgmc/data/hdf5_loader.py
jax_sgmc/data/numpy_loader.py
jax_sgmc/data/tensorflow_loader.py
jax_sgmc/util/__init__.py
jax_sgmc/util/list_map.py
jax_sgmc/util/stop_vmap.py
jax_sgmc/util/testing.py
jax_sgmc/util/tree_util.py
jax_sgmc/util/uuid.py
jax_sgmc-0.1.5.dist-info/LICENSE
jax_sgmc-0.1.5.dist-info/LICENSE_SHORT
jax_sgmc-0.1.5.dist-info/METADATA
jax_sgmc-0.1.5.dist-info/WHEEL
jax_sgmc-0.1.5.dist-info/top_level.txt
jax_sgmc-0.1.5.dist-info/RECORD
