Metadata-Version: 2.1
Name: jax-sgmc
Version: 0.1.5
Summary: Stochastic Gradient Monte Carlo in Jax
Author-email: Paul Fuchs <paul.fuchs@tum.de>, Stephan Thaler <stephan.thaler@tum.de>
License: Apache-2.0
Project-URL: Documentation, https://jax-sgmc.readthedocs.io/en/latest/
Project-URL: Source, https://github.com/tummfm/jax-sgmc
Project-URL: Bug Tracker, https://github.com/tummfm/jax-sgmc/issues
Classifier: Programming Language :: Python :: 3.8
Classifier: Programming Language :: Python :: 3.9
Classifier: License :: OSI Approved :: Apache Software License
Classifier: Operating System :: MacOS
Classifier: Operating System :: POSIX :: Linux
Classifier: Topic :: Scientific/Engineering
Classifier: Intended Audience :: Science/Research
Classifier: Intended Audience :: Developers
Requires-Python: >=3.7
License-File: LICENSE
License-File: LICENSE_SHORT
Requires-Dist: numpy
Requires-Dist: jax >=0.1.73
Requires-Dist: jaxlib >=0.1.52
Requires-Dist: dataclasses
Provides-Extra: docs
Requires-Dist: sphinx >=3 ; extra == 'docs'
Requires-Dist: sphinx-rtd-theme ; extra == 'docs'
Requires-Dist: sphinx-autodoc-typehints ==1.11.1 ; extra == 'docs'
Requires-Dist: myst-nb ; extra == 'docs'
Requires-Dist: numpyro ; extra == 'docs'
Requires-Dist: matplotlib ; extra == 'docs'
Requires-Dist: h5py ; extra == 'docs'
Requires-Dist: tensorflow ; extra == 'docs'
Requires-Dist: tensorflow-datasets ; extra == 'docs'
Provides-Extra: tensorflow
Requires-Dist: tensorflow ; extra == 'tensorflow'
Requires-Dist: tensorflow-datasets ; extra == 'tensorflow'
Provides-Extra: test
Requires-Dist: pylint ; extra == 'test'
Requires-Dist: pytest ; extra == 'test'
Requires-Dist: pytest-mock ; extra == 'test'
